<annotation>
        <folder>FOLDER</folder>
        <filename>609388647.jpg</filename>
        <path>one_card_out/609388647.jpg</path>
        <source>
                <database>Unknown</database>
        </source>
        <size>
                <width>720</width>
                <height>720</height>
                <depth>3</depth>
        </size>
 <object>
                <name>s_6.png</name>
                <pose>Unspecified</pose>
                <truncated>0</truncated>
                <difficult>0</difficult>
                <bndbox>
                        <xmin>110</xmin>
                        <ymin>292</ymin>
                        <xmax>172</xmax>
                        <ymax>362</ymax>
                </bndbox>
        </object>
 <object>
                <name>s_6.png</name>
                <pose>Unspecified</pose>
                <truncated>0</truncated>
                <difficult>0</difficult>
                <bndbox>
                        <xmin>268</xmin>
                        <ymin>241</ymin>
                        <xmax>330</xmax>
                        <ymax>312</ymax>
                </bndbox>
        </object>
</annotation>        
