<annotation>
        <folder>FOLDER</folder>
        <filename>676280045.jpg</filename>
        <path>one_card_out/676280045.jpg</path>
        <source>
                <database>Unknown</database>
        </source>
        <size>
                <width>720</width>
                <height>720</height>
                <depth>3</depth>
        </size>
 <object>
                <name>c_k.png</name>
                <pose>Unspecified</pose>
                <truncated>0</truncated>
                <difficult>0</difficult>
                <bndbox>
                        <xmin>323</xmin>
                        <ymin>531</ymin>
                        <xmax>407</xmax>
                        <ymax>611</ymax>
                </bndbox>
        </object>
 <object>
                <name>c_k.png</name>
                <pose>Unspecified</pose>
                <truncated>0</truncated>
                <difficult>0</difficult>
                <bndbox>
                        <xmin>200</xmin>
                        <ymin>421</ymin>
                        <xmax>284</xmax>
                        <ymax>501</ymax>
                </bndbox>
        </object>
</annotation>        
