<annotation>
        <folder>FOLDER</folder>
        <filename>949476352.jpg</filename>
        <path>one_card_out/949476352.jpg</path>
        <source>
                <database>Unknown</database>
        </source>
        <size>
                <width>720</width>
                <height>720</height>
                <depth>3</depth>
        </size>
 <object>
                <name>s_10.png</name>
                <pose>Unspecified</pose>
                <truncated>0</truncated>
                <difficult>0</difficult>
                <bndbox>
                        <xmin>460</xmin>
                        <ymin>528</ymin>
                        <xmax>584</xmax>
                        <ymax>644</ymax>
                </bndbox>
        </object>
 <object>
                <name>s_10.png</name>
                <pose>Unspecified</pose>
                <truncated>0</truncated>
                <difficult>0</difficult>
                <bndbox>
                        <xmin>282</xmin>
                        <ymin>347</ymin>
                        <xmax>405</xmax>
                        <ymax>463</ymax>
                </bndbox>
        </object>
</annotation>        
